MANIFEST.in
README.rst
VERSION
setup.py
statuspageio/__init__.py
statuspageio/client.py
statuspageio/configuration.py
statuspageio/errors.py
statuspageio/http_client.py
statuspageio/services.py
statuspageio/version.py
statuspageio.egg-info/PKG-INFO
statuspageio.egg-info/SOURCES.txt
statuspageio.egg-info/dependency_links.txt
statuspageio.egg-info/requires.txt
statuspageio.egg-info/top_level.txt